[
  {
    "code": "x = 0\nx = int(np.sqrt(x))\nx *= 2\nx %= 9\nx **= 2\nx -= 1\nx //= 2\nx = int(np.abs(x - 9))\nx **= 2\nx -= 9\nx = int(np.sqrt(x))\nx -= 5",
    "intermediate": [
      0,
      0,
      0,
      0,
      -1,
      -1,
      10,
      100,
      91,
      9,
      4
    ],
    "true_val": 4,
    "pred_int": 4,
    "outputs": [
      {
        "generated_text": "You are given a short Python program. Your task is to compute the final value of the variable x. Return only the integer, without commas, an equal sign, or any additional text. The integer should appear immediately after the word 'is: '.\n\n```python\nx = 0\nx = int(np.sqrt(x))\nx *= 2\nx %= 9\nx **= 2\nx -= 1\nx //= 2\nx = int(np.abs(x - 9))\nx **= 2\nx -= 9\nx = int(np.sqrt(x))\nx -= 5\n```The final value of x is: 6\n```\n\n### Notes\n\n-"
      },
      {
        "generated_text": "You are given a short Python program. Your task is to compute the final value of the variable x. Return only the integer, without commas, an equal sign, or any additional text. The integer should appear immediately after the word 'is: '.\n\n```python\nx = 0\nx = int(np.sqrt(x))\nx *= 2\nx %= 9\nx **= 2\nx -= 1\nx //= 2\nx = int(np.abs(x - 9))\nx **= 2\nx -= 9\nx = int(np.sqrt(x))\nx -= 5\n```The final value of x is: \n```\n\nExample:\nInput:\n"
      },
      {
        "generated_text": "You are given a short Python program. Your task is to compute the final value of the variable x. Return only the integer, without commas, an equal sign, or any additional text. The integer should appear immediately after the word 'is: '.\n\n```python\nx = 0\nx = int(np.sqrt(x))\nx *= 2\nx %= 9\nx **= 2\nx -= 1\nx //= 2\nx = int(np.abs(x - 9))\nx **= 2\nx -= 9\nx = int(np.sqrt(x))\nx -= 5\n```The final value of x is: \n\nInput: None\n\nOutput: The final value"
      },
      {
        "generated_text": "You are given a short Python program. Your task is to compute the final value of the variable x. Return only the integer, without commas, an equal sign, or any additional text. The integer should appear immediately after the word 'is: '.\n\n```python\nx = 0\nx = int(np.sqrt(x))\nx *= 2\nx %= 9\nx **= 2\nx -= 1\nx //= 2\nx = int(np.abs(x - 9))\nx **= 2\nx -= 9\nx = int(np.sqrt(x))\nx -= 5\n```The final value of x is: 4\n\nNote: The given Python program is incomplete"
      },
      {
        "generated_text": "You are given a short Python program. Your task is to compute the final value of the variable x. Return only the integer, without commas, an equal sign, or any additional text. The integer should appear immediately after the word 'is: '.\n\n```python\nx = 0\nx = int(np.sqrt(x))\nx *= 2\nx %= 9\nx **= 2\nx -= 1\nx //= 2\nx = int(np.abs(x - 9))\nx **= 2\nx -= 9\nx = int(np.sqrt(x))\nx -= 5\n```The final value of x is: 16."
      },
      {
        "generated_text": "You are given a short Python program. Your task is to compute the final value of the variable x. Return only the integer, without commas, an equal sign, or any additional text. The integer should appear immediately after the word 'is: '.\n\n```python\nx = 0\nx = int(np.sqrt(x))\nx *= 2\nx %= 9\nx **= 2\nx -= 1\nx //= 2\nx = int(np.abs(x - 9))\nx **= 2\nx -= 9\nx = int(np.sqrt(x))\nx -= 5\n```The final value of x is: \n```python\n# 1\n``"
      },
      {
        "generated_text": "You are given a short Python program. Your task is to compute the final value of the variable x. Return only the integer, without commas, an equal sign, or any additional text. The integer should appear immediately after the word 'is: '.\n\n```python\nx = 0\nx = int(np.sqrt(x))\nx *= 2\nx %= 9\nx **= 2\nx -= 1\nx //= 2\nx = int(np.abs(x - 9))\nx **= 2\nx -= 9\nx = int(np.sqrt(x))\nx -= 5\n```The final value of x is: 8\n```\n\n**Input**\nThe"
      },
      {
        "generated_text": "You are given a short Python program. Your task is to compute the final value of the variable x. Return only the integer, without commas, an equal sign, or any additional text. The integer should appear immediately after the word 'is: '.\n\n```python\nx = 0\nx = int(np.sqrt(x))\nx *= 2\nx %= 9\nx **= 2\nx -= 1\nx //= 2\nx = int(np.abs(x - 9))\nx **= 2\nx -= 9\nx = int(np.sqrt(x))\nx -= 5\n```The final value of x is: \n\n```python\nprint(x)\n"
      },
      {
        "generated_text": "You are given a short Python program. Your task is to compute the final value of the variable x. Return only the integer, without commas, an equal sign, or any additional text. The integer should appear immediately after the word 'is: '.\n\n```python\nx = 0\nx = int(np.sqrt(x))\nx *= 2\nx %= 9\nx **= 2\nx -= 1\nx //= 2\nx = int(np.abs(x - 9))\nx **= 2\nx -= 9\nx = int(np.sqrt(x))\nx -= 5\n```The final value of x is: 0."
      },
      {
        "generated_text": "You are given a short Python program. Your task is to compute the final value of the variable x. Return only the integer, without commas, an equal sign, or any additional text. The integer should appear immediately after the word 'is: '.\n\n```python\nx = 0\nx = int(np.sqrt(x))\nx *= 2\nx %= 9\nx **= 2\nx -= 1\nx //= 2\nx = int(np.abs(x - 9))\nx **= 2\nx -= 9\nx = int(np.sqrt(x))\nx -= 5\n```The final value of x is: \n```\n\nExample:\nInput: "
      }
    ],
    "correct": true
  },
  {
    "code": "x = 0\nx -= 7\nx = int(np.abs(x - 8))\nx += 8\nx = int(np.abs(x - 3))\nx = int(np.sqrt(x))\nx //= 6\nx = int(np.sqrt(x))\nx -= 2\nx **= 2\nx = int(np.sqrt(x))",
    "intermediate": [
      -7,
      15,
      23,
      20,
      4,
      0,
      0,
      -2,
      4,
      2
    ],
    "true_val": 2,
    "pred_int": 2,
    "outputs": [
      {
        "generated_text": "You are given a short Python program. Your task is to compute the final value of the variable x. Return only the integer, without commas, an equal sign, or any additional text. The integer should appear immediately after the word 'is: '.\n\n```python\nx = 0\nx -= 7\nx = int(np.abs(x - 8))\nx += 8\nx = int(np.abs(x - 3))\nx = int(np.sqrt(x))\nx //= 6\nx = int(np.sqrt(x))\nx -= 2\nx **= 2\nx = int(np.sqrt(x))\n```The final value of x is: 3\n```\n\n```python\nx"
      },
      {
        "generated_text": "You are given a short Python program. Your task is to compute the final value of the variable x. Return only the integer, without commas, an equal sign, or any additional text. The integer should appear immediately after the word 'is: '.\n\n```python\nx = 0\nx -= 7\nx = int(np.abs(x - 8))\nx += 8\nx = int(np.abs(x - 3))\nx = int(np.sqrt(x))\nx //= 6\nx = int(np.sqrt(x))\nx -= 2\nx **= 2\nx = int(np.sqrt(x))\n```The final value of x is: 2.\n```python\n# Complete the"
      },
      {
        "generated_text": "You are given a short Python program. Your task is to compute the final value of the variable x. Return only the integer, without commas, an equal sign, or any additional text. The integer should appear immediately after the word 'is: '.\n\n```python\nx = 0\nx -= 7\nx = int(np.abs(x - 8))\nx += 8\nx = int(np.abs(x - 3))\nx = int(np.sqrt(x))\nx //= 6\nx = int(np.sqrt(x))\nx -= 2\nx **= 2\nx = int(np.sqrt(x))\n```The final value of x is: 1\n```python\nprint(f\""
      },
      {
        "generated_text": "You are given a short Python program. Your task is to compute the final value of the variable x. Return only the integer, without commas, an equal sign, or any additional text. The integer should appear immediately after the word 'is: '.\n\n```python\nx = 0\nx -= 7\nx = int(np.abs(x - 8))\nx += 8\nx = int(np.abs(x - 3))\nx = int(np.sqrt(x))\nx //= 6\nx = int(np.sqrt(x))\nx -= 2\nx **= 2\nx = int(np.sqrt(x))\n```The final value of x is: 0"
      },
      {
        "generated_text": "You are given a short Python program. Your task is to compute the final value of the variable x. Return only the integer, without commas, an equal sign, or any additional text. The integer should appear immediately after the word 'is: '.\n\n```python\nx = 0\nx -= 7\nx = int(np.abs(x - 8))\nx += 8\nx = int(np.abs(x - 3))\nx = int(np.sqrt(x))\nx //= 6\nx = int(np.sqrt(x))\nx -= 2\nx **= 2\nx = int(np.sqrt(x))\n```The final value of x is: \n\n```python\nx = 0\n"
      },
      {
        "generated_text": "You are given a short Python program. Your task is to compute the final value of the variable x. Return only the integer, without commas, an equal sign, or any additional text. The integer should appear immediately after the word 'is: '.\n\n```python\nx = 0\nx -= 7\nx = int(np.abs(x - 8))\nx += 8\nx = int(np.abs(x - 3))\nx = int(np.sqrt(x))\nx //= 6\nx = int(np.sqrt(x))\nx -= 2\nx **= 2\nx = int(np.sqrt(x))\n```The final value of x is: 5"
      },
      {
        "generated_text": "You are given a short Python program. Your task is to compute the final value of the variable x. Return only the integer, without commas, an equal sign, or any additional text. The integer should appear immediately after the word 'is: '.\n\n```python\nx = 0\nx -= 7\nx = int(np.abs(x - 8))\nx += 8\nx = int(np.abs(x - 3))\nx = int(np.sqrt(x))\nx //= 6\nx = int(np.sqrt(x))\nx -= 2\nx **= 2\nx = int(np.sqrt(x))\n```The final value of x is: 3\n```python\nx = 0"
      },
      {
        "generated_text": "You are given a short Python program. Your task is to compute the final value of the variable x. Return only the integer, without commas, an equal sign, or any additional text. The integer should appear immediately after the word 'is: '.\n\n```python\nx = 0\nx -= 7\nx = int(np.abs(x - 8))\nx += 8\nx = int(np.abs(x - 3))\nx = int(np.sqrt(x))\nx //= 6\nx = int(np.sqrt(x))\nx -= 2\nx **= 2\nx = int(np.sqrt(x))\n```The final value of x is: \n\n(Your code here)\n\nYour solution should"
      },
      {
        "generated_text": "You are given a short Python program. Your task is to compute the final value of the variable x. Return only the integer, without commas, an equal sign, or any additional text. The integer should appear immediately after the word 'is: '.\n\n```python\nx = 0\nx -= 7\nx = int(np.abs(x - 8))\nx += 8\nx = int(np.abs(x - 3))\nx = int(np.sqrt(x))\nx //= 6\nx = int(np.sqrt(x))\nx -= 2\nx **= 2\nx = int(np.sqrt(x))\n```The final value of x is: 2\n```python\nx = 0"
      },
      {
        "generated_text": "You are given a short Python program. Your task is to compute the final value of the variable x. Return only the integer, without commas, an equal sign, or any additional text. The integer should appear immediately after the word 'is: '.\n\n```python\nx = 0\nx -= 7\nx = int(np.abs(x - 8))\nx += 8\nx = int(np.abs(x - 3))\nx = int(np.sqrt(x))\nx //= 6\nx = int(np.sqrt(x))\nx -= 2\nx **= 2\nx = int(np.sqrt(x))\n```The final value of x is: 11```\n\nYour function should return: "
      }
    ],
    "correct": true
  },
  {
    "code": "x = 0\nx = int(np.sqrt(x))\nx **= 2\nx //= 3\nx = int(np.abs(x - 1))\nx += 7\nx = int(np.sqrt(x))\nx %= 3\nx -= 2\nx %= 1\nx = int(np.sqrt(x))\nx += 3",
    "intermediate": [
      0,
      0,
      0,
      1,
      8,
      2,
      2,
      0,
      0,
      0,
      3
    ],
    "true_val": 3,
    "pred_int": 3,
    "outputs": [
      {
        "generated_text": "You are given a short Python program. Your task is to compute the final value of the variable x. Return only the integer, without commas, an equal sign, or any additional text. The integer should appear immediately after the word 'is: '.\n\n```python\nx = 0\nx = int(np.sqrt(x))\nx **= 2\nx //= 3\nx = int(np.abs(x - 1))\nx += 7\nx = int(np.sqrt(x))\nx %= 3\nx -= 2\nx %= 1\nx = int(np.sqrt(x))\nx += 3\n```The final value of x is: \n```\n\nWrite a function `compute"
      },
      {
        "generated_text": "You are given a short Python program. Your task is to compute the final value of the variable x. Return only the integer, without commas, an equal sign, or any additional text. The integer should appear immediately after the word 'is: '.\n\n```python\nx = 0\nx = int(np.sqrt(x))\nx **= 2\nx //= 3\nx = int(np.abs(x - 1))\nx += 7\nx = int(np.sqrt(x))\nx %= 3\nx -= 2\nx %= 1\nx = int(np.sqrt(x))\nx += 3\n```The final value of x is: \n```\n\nExample:\n\nInput:\n"
      },
      {
        "generated_text": "You are given a short Python program. Your task is to compute the final value of the variable x. Return only the integer, without commas, an equal sign, or any additional text. The integer should appear immediately after the word 'is: '.\n\n```python\nx = 0\nx = int(np.sqrt(x))\nx **= 2\nx //= 3\nx = int(np.abs(x - 1))\nx += 7\nx = int(np.sqrt(x))\nx %= 3\nx -= 2\nx %= 1\nx = int(np.sqrt(x))\nx += 3\n```The final value of x is: 3\n```python\n\n```python\n\n"
      },
      {
        "generated_text": "You are given a short Python program. Your task is to compute the final value of the variable x. Return only the integer, without commas, an equal sign, or any additional text. The integer should appear immediately after the word 'is: '.\n\n```python\nx = 0\nx = int(np.sqrt(x))\nx **= 2\nx //= 3\nx = int(np.abs(x - 1))\nx += 7\nx = int(np.sqrt(x))\nx %= 3\nx -= 2\nx %= 1\nx = int(np.sqrt(x))\nx += 3\n```The final value of x is: 1."
      },
      {
        "generated_text": "You are given a short Python program. Your task is to compute the final value of the variable x. Return only the integer, without commas, an equal sign, or any additional text. The integer should appear immediately after the word 'is: '.\n\n```python\nx = 0\nx = int(np.sqrt(x))\nx **= 2\nx //= 3\nx = int(np.abs(x - 1))\nx += 7\nx = int(np.sqrt(x))\nx %= 3\nx -= 2\nx %= 1\nx = int(np.sqrt(x))\nx += 3\n```The final value of x is: 4```"
      },
      {
        "generated_text": "You are given a short Python program. Your task is to compute the final value of the variable x. Return only the integer, without commas, an equal sign, or any additional text. The integer should appear immediately after the word 'is: '.\n\n```python\nx = 0\nx = int(np.sqrt(x))\nx **= 2\nx //= 3\nx = int(np.abs(x - 1))\nx += 7\nx = int(np.sqrt(x))\nx %= 3\nx -= 2\nx %= 1\nx = int(np.sqrt(x))\nx += 3\n```The final value of x is: \n```\n\n# Input:\nThe input"
      },
      {
        "generated_text": "You are given a short Python program. Your task is to compute the final value of the variable x. Return only the integer, without commas, an equal sign, or any additional text. The integer should appear immediately after the word 'is: '.\n\n```python\nx = 0\nx = int(np.sqrt(x))\nx **= 2\nx //= 3\nx = int(np.abs(x - 1))\nx += 7\nx = int(np.sqrt(x))\nx %= 3\nx -= 2\nx %= 1\nx = int(np.sqrt(x))\nx += 3\n```The final value of x is: 4\n```python\nx = 0"
      },
      {
        "generated_text": "You are given a short Python program. Your task is to compute the final value of the variable x. Return only the integer, without commas, an equal sign, or any additional text. The integer should appear immediately after the word 'is: '.\n\n```python\nx = 0\nx = int(np.sqrt(x))\nx **= 2\nx //= 3\nx = int(np.abs(x - 1))\nx += 7\nx = int(np.sqrt(x))\nx %= 3\nx -= 2\nx %= 1\nx = int(np.sqrt(x))\nx += 3\n```The final value of x is: \n```python\nx\n```\n\n"
      },
      {
        "generated_text": "You are given a short Python program. Your task is to compute the final value of the variable x. Return only the integer, without commas, an equal sign, or any additional text. The integer should appear immediately after the word 'is: '.\n\n```python\nx = 0\nx = int(np.sqrt(x))\nx **= 2\nx //= 3\nx = int(np.abs(x - 1))\nx += 7\nx = int(np.sqrt(x))\nx %= 3\nx -= 2\nx %= 1\nx = int(np.sqrt(x))\nx += 3\n```The final value of x is: 1\n```python\n```"
      },
      {
        "generated_text": "You are given a short Python program. Your task is to compute the final value of the variable x. Return only the integer, without commas, an equal sign, or any additional text. The integer should appear immediately after the word 'is: '.\n\n```python\nx = 0\nx = int(np.sqrt(x))\nx **= 2\nx //= 3\nx = int(np.abs(x - 1))\nx += 7\nx = int(np.sqrt(x))\nx %= 3\nx -= 2\nx %= 1\nx = int(np.sqrt(x))\nx += 3\n```The final value of x is: \n```\n\nExample:\nInput:\n"
      }
    ],
    "correct": true
  },
  {
    "code": "x = 0\nx %= 1\nx = int(np.abs(x - 3))\nx += 8\nx %= 4",
    "intermediate": [
      0,
      3,
      11,
      3
    ],
    "true_val": 3,
    "pred_int": 3,
    "outputs": [
      {
        "generated_text": "You are given a short Python program. Your task is to compute the final value of the variable x. Return only the integer, without commas, an equal sign, or any additional text. The integer should appear immediately after the word 'is: '.\n\n```python\nx = 0\nx %= 1\nx = int(np.abs(x - 3))\nx += 8\nx %= 4\n```The final value of x is: 3\n\nYour function should return the integer 3"
      },
      {
        "generated_text": "You are given a short Python program. Your task is to compute the final value of the variable x. Return only the integer, without commas, an equal sign, or any additional text. The integer should appear immediately after the word 'is: '.\n\n```python\nx = 0\nx %= 1\nx = int(np.abs(x - 3))\nx += 8\nx %= 4\n```The final value of x is: \n```\n1\n```\n\nNote"
      },
      {
        "generated_text": "You are given a short Python program. Your task is to compute the final value of the variable x. Return only the integer, without commas, an equal sign, or any additional text. The integer should appear immediately after the word 'is: '.\n\n```python\nx = 0\nx %= 1\nx = int(np.abs(x - 3))\nx += 8\nx %= 4\n```The final value of x is: 3. Your program must return '3'."
      },
      {
        "generated_text": "You are given a short Python program. Your task is to compute the final value of the variable x. Return only the integer, without commas, an equal sign, or any additional text. The integer should appear immediately after the word 'is: '.\n\n```python\nx = 0\nx %= 1\nx = int(np.abs(x - 3))\nx += 8\nx %= 4\n```The final value of x is: \n\nYour task is to write a Python function that"
      },
      {
        "generated_text": "You are given a short Python program. Your task is to compute the final value of the variable x. Return only the integer, without commas, an equal sign, or any additional text. The integer should appear immediately after the word 'is: '.\n\n```python\nx = 0\nx %= 1\nx = int(np.abs(x - 3))\nx += 8\nx %= 4\n```The final value of x is: 3"
      },
      {
        "generated_text": "You are given a short Python program. Your task is to compute the final value of the variable x. Return only the integer, without commas, an equal sign, or any additional text. The integer should appear immediately after the word 'is: '.\n\n```python\nx = 0\nx %= 1\nx = int(np.abs(x - 3))\nx += 8\nx %= 4\n```The final value of x is: 0\n\n```python\nx = 10"
      },
      {
        "generated_text": "You are given a short Python program. Your task is to compute the final value of the variable x. Return only the integer, without commas, an equal sign, or any additional text. The integer should appear immediately after the word 'is: '.\n\n```python\nx = 0\nx %= 1\nx = int(np.abs(x - 3))\nx += 8\nx %= 4\n```The final value of x is: 2\n\nNote:\n- np is a module"
      },
      {
        "generated_text": "You are given a short Python program. Your task is to compute the final value of the variable x. Return only the integer, without commas, an equal sign, or any additional text. The integer should appear immediately after the word 'is: '.\n\n```python\nx = 0\nx %= 1\nx = int(np.abs(x - 3))\nx += 8\nx %= 4\n```The final value of x is: 3\n```python\n# Your task is"
      },
      {
        "generated_text": "You are given a short Python program. Your task is to compute the final value of the variable x. Return only the integer, without commas, an equal sign, or any additional text. The integer should appear immediately after the word 'is: '.\n\n```python\nx = 0\nx %= 1\nx = int(np.abs(x - 3))\nx += 8\nx %= 4\n```The final value of x is: 8"
      },
      {
        "generated_text": "You are given a short Python program. Your task is to compute the final value of the variable x. Return only the integer, without commas, an equal sign, or any additional text. The integer should appear immediately after the word 'is: '.\n\n```python\nx = 0\nx %= 1\nx = int(np.abs(x - 3))\nx += 8\nx %= 4\n```The final value of x is: \n```\n\n### Created Chinese Question\n"
      }
    ],
    "correct": true
  },
  {
    "code": "x = 0\nx //= 3\nx = int(np.abs(x - 8))\nx *= 1\nx += 1",
    "intermediate": [
      0,
      8,
      8,
      9
    ],
    "true_val": 9,
    "pred_int": 3,
    "outputs": [
      {
        "generated_text": "You are given a short Python program. Your task is to compute the final value of the variable x. Return only the integer, without commas, an equal sign, or any additional text. The integer should appear immediately after the word 'is: '.\n\n```python\nx = 0\nx //= 3\nx = int(np.abs(x - 8))\nx *= 1\nx += 1\n```The final value of x is: 3.\n\nYour solution should be in the following"
      },
      {
        "generated_text": "You are given a short Python program. Your task is to compute the final value of the variable x. Return only the integer, without commas, an equal sign, or any additional text. The integer should appear immediately after the word 'is: '.\n\n```python\nx = 0\nx //= 3\nx = int(np.abs(x - 8))\nx *= 1\nx += 1\n```The final value of x is: 1\n\nNote: The input to your function will"
      },
      {
        "generated_text": "You are given a short Python program. Your task is to compute the final value of the variable x. Return only the integer, without commas, an equal sign, or any additional text. The integer should appear immediately after the word 'is: '.\n\n```python\nx = 0\nx //= 3\nx = int(np.abs(x - 8))\nx *= 1\nx += 1\n```The final value of x is: 2"
      },
      {
        "generated_text": "You are given a short Python program. Your task is to compute the final value of the variable x. Return only the integer, without commas, an equal sign, or any additional text. The integer should appear immediately after the word 'is: '.\n\n```python\nx = 0\nx //= 3\nx = int(np.abs(x - 8))\nx *= 1\nx += 1\n```The final value of x is: 4."
      },
      {
        "generated_text": "You are given a short Python program. Your task is to compute the final value of the variable x. Return only the integer, without commas, an equal sign, or any additional text. The integer should appear immediately after the word 'is: '.\n\n```python\nx = 0\nx //= 3\nx = int(np.abs(x - 8))\nx *= 1\nx += 1\n```The final value of x is: 3\n\nExamples:\n```python\n"
      },
      {
        "generated_text": "You are given a short Python program. Your task is to compute the final value of the variable x. Return only the integer, without commas, an equal sign, or any additional text. The integer should appear immediately after the word 'is: '.\n\n```python\nx = 0\nx //= 3\nx = int(np.abs(x - 8))\nx *= 1\nx += 1\n```The final value of x is: 4."
      },
      {
        "generated_text": "You are given a short Python program. Your task is to compute the final value of the variable x. Return only the integer, without commas, an equal sign, or any additional text. The integer should appear immediately after the word 'is: '.\n\n```python\nx = 0\nx //= 3\nx = int(np.abs(x - 8))\nx *= 1\nx += 1\n```The final value of x is: 3\n\nYour task is to write a function that"
      },
      {
        "generated_text": "You are given a short Python program. Your task is to compute the final value of the variable x. Return only the integer, without commas, an equal sign, or any additional text. The integer should appear immediately after the word 'is: '.\n\n```python\nx = 0\nx //= 3\nx = int(np.abs(x - 8))\nx *= 1\nx += 1\n```The final value of x is: 5\n\nUse the following starter code to write the"
      },
      {
        "generated_text": "You are given a short Python program. Your task is to compute the final value of the variable x. Return only the integer, without commas, an equal sign, or any additional text. The integer should appear immediately after the word 'is: '.\n\n```python\nx = 0\nx //= 3\nx = int(np.abs(x - 8))\nx *= 1\nx += 1\n```The final value of x is: \n\n(Note: The actual final value of x"
      },
      {
        "generated_text": "You are given a short Python program. Your task is to compute the final value of the variable x. Return only the integer, without commas, an equal sign, or any additional text. The integer should appear immediately after the word 'is: '.\n\n```python\nx = 0\nx //= 3\nx = int(np.abs(x - 8))\nx *= 1\nx += 1\n```The final value of x is: 3\n\n# Your code here\n```\n\n"
      }
    ],
    "correct": false
  },
  {
    "code": "x = 0\nx -= 9\nx %= 3\nx += 5\nx //= 6",
    "intermediate": [
      -9,
      0,
      5,
      0
    ],
    "true_val": 0,
    "pred_int": 0,
    "outputs": [
      {
        "generated_text": "You are given a short Python program. Your task is to compute the final value of the variable x. Return only the integer, without commas, an equal sign, or any additional text. The integer should appear immediately after the word 'is: '.\n\n```python\nx = 0\nx -= 9\nx %= 3\nx += 5\nx //= 6\n```The final value of x is: 2."
      },
      {
        "generated_text": "You are given a short Python program. Your task is to compute the final value of the variable x. Return only the integer, without commas, an equal sign, or any additional text. The integer should appear immediately after the word 'is: '.\n\n```python\nx = 0\nx -= 9\nx %= 3\nx += 5\nx //= 6\n```The final value of x is: 0\n```\n\nExample 2:\n"
      },
      {
        "generated_text": "You are given a short Python program. Your task is to compute the final value of the variable x. Return only the integer, without commas, an equal sign, or any additional text. The integer should appear immediately after the word 'is: '.\n\n```python\nx = 0\nx -= 9\nx %= 3\nx += 5\nx //= 6\n```The final value of x is: \n```python\nx = 0 -"
      },
      {
        "generated_text": "You are given a short Python program. Your task is to compute the final value of the variable x. Return only the integer, without commas, an equal sign, or any additional text. The integer should appear immediately after the word 'is: '.\n\n```python\nx = 0\nx -= 9\nx %= 3\nx += 5\nx //= 6\n```The final value of x is: 2."
      },
      {
        "generated_text": "You are given a short Python program. Your task is to compute the final value of the variable x. Return only the integer, without commas, an equal sign, or any additional text. The integer should appear immediately after the word 'is: '.\n\n```python\nx = 0\nx -= 9\nx %= 3\nx += 5\nx //= 6\n```The final value of x is: 1\n\nNote: In the Python program, you"
      },
      {
        "generated_text": "You are given a short Python program. Your task is to compute the final value of the variable x. Return only the integer, without commas, an equal sign, or any additional text. The integer should appear immediately after the word 'is: '.\n\n```python\nx = 0\nx -= 9\nx %= 3\nx += 5\nx //= 6\n```The final value of x is: \n```\n\n### Constraints\n\n-"
      },
      {
        "generated_text": "You are given a short Python program. Your task is to compute the final value of the variable x. Return only the integer, without commas, an equal sign, or any additional text. The integer should appear immediately after the word 'is: '.\n\n```python\nx = 0\nx -= 9\nx %= 3\nx += 5\nx //= 6\n```The final value of x is: 0."
      },
      {
        "generated_text": "You are given a short Python program. Your task is to compute the final value of the variable x. Return only the integer, without commas, an equal sign, or any additional text. The integer should appear immediately after the word 'is: '.\n\n```python\nx = 0\nx -= 9\nx %= 3\nx += 5\nx //= 6\n```The final value of x is: \n```python\nis: 0\n"
      },
      {
        "generated_text": "You are given a short Python program. Your task is to compute the final value of the variable x. Return only the integer, without commas, an equal sign, or any additional text. The integer should appear immediately after the word 'is: '.\n\n```python\nx = 0\nx -= 9\nx %= 3\nx += 5\nx //= 6\n```The final value of x is: \n\nThe output should be: \n\nThe Python"
      },
      {
        "generated_text": "You are given a short Python program. Your task is to compute the final value of the variable x. Return only the integer, without commas, an equal sign, or any additional text. The integer should appear immediately after the word 'is: '.\n\n```python\nx = 0\nx -= 9\nx %= 3\nx += 5\nx //= 6\n```The final value of x is: 2\n```python\nx = 0"
      }
    ],
    "correct": true
  },
  {
    "code": "x = 0\nx **= 2\nx = int(np.abs(x - 5))\nx //= 6\nx += 3",
    "intermediate": [
      0,
      5,
      0,
      3
    ],
    "true_val": 3,
    "pred_int": 0,
    "outputs": [
      {
        "generated_text": "You are given a short Python program. Your task is to compute the final value of the variable x. Return only the integer, without commas, an equal sign, or any additional text. The integer should appear immediately after the word 'is: '.\n\n```python\nx = 0\nx **= 2\nx = int(np.abs(x - 5))\nx //= 6\nx += 3\n```The final value of x is: \n\nNote: Your task is to return the final"
      },
      {
        "generated_text": "You are given a short Python program. Your task is to compute the final value of the variable x. Return only the integer, without commas, an equal sign, or any additional text. The integer should appear immediately after the word 'is: '.\n\n```python\nx = 0\nx **= 2\nx = int(np.abs(x - 5))\nx //= 6\nx += 3\n```The final value of x is: \n```\n# Hint: You might"
      },
      {
        "generated_text": "You are given a short Python program. Your task is to compute the final value of the variable x. Return only the integer, without commas, an equal sign, or any additional text. The integer should appear immediately after the word 'is: '.\n\n```python\nx = 0\nx **= 2\nx = int(np.abs(x - 5))\nx //= 6\nx += 3\n```The final value of x is: \n\nNote: In this question, x is an"
      },
      {
        "generated_text": "You are given a short Python program. Your task is to compute the final value of the variable x. Return only the integer, without commas, an equal sign, or any additional text. The integer should appear immediately after the word 'is: '.\n\n```python\nx = 0\nx **= 2\nx = int(np.abs(x - 5))\nx //= 6\nx += 3\n```The final value of x is: 0\n\nWrite a function or method to solve this"
      },
      {
        "generated_text": "You are given a short Python program. Your task is to compute the final value of the variable x. Return only the integer, without commas, an equal sign, or any additional text. The integer should appear immediately after the word 'is: '.\n\n```python\nx = 0\nx **= 2\nx = int(np.abs(x - 5))\nx //= 6\nx += 3\n```The final value of x is: 1```\n\nWrite a function named calculate_"
      },
      {
        "generated_text": "You are given a short Python program. Your task is to compute the final value of the variable x. Return only the integer, without commas, an equal sign, or any additional text. The integer should appear immediately after the word 'is: '.\n\n```python\nx = 0\nx **= 2\nx = int(np.abs(x - 5))\nx //= 6\nx += 3\n```The final value of x is: \n```\n\nExample:\nInput: "
      },
      {
        "generated_text": "You are given a short Python program. Your task is to compute the final value of the variable x. Return only the integer, without commas, an equal sign, or any additional text. The integer should appear immediately after the word 'is: '.\n\n```python\nx = 0\nx **= 2\nx = int(np.abs(x - 5))\nx //= 6\nx += 3\n```The final value of x is: \n```\n\nInput: None\nOutput:"
      },
      {
        "generated_text": "You are given a short Python program. Your task is to compute the final value of the variable x. Return only the integer, without commas, an equal sign, or any additional text. The integer should appear immediately after the word 'is: '.\n\n```python\nx = 0\nx **= 2\nx = int(np.abs(x - 5))\nx //= 6\nx += 3\n```The final value of x is: 1\n\nYour function should return: '1'"
      },
      {
        "generated_text": "You are given a short Python program. Your task is to compute the final value of the variable x. Return only the integer, without commas, an equal sign, or any additional text. The integer should appear immediately after the word 'is: '.\n\n```python\nx = 0\nx **= 2\nx = int(np.abs(x - 5))\nx //= 6\nx += 3\n```The final value of x is: 0\n```python\nx = 0"
      },
      {
        "generated_text": "You are given a short Python program. Your task is to compute the final value of the variable x. Return only the integer, without commas, an equal sign, or any additional text. The integer should appear immediately after the word 'is: '.\n\n```python\nx = 0\nx **= 2\nx = int(np.abs(x - 5))\nx //= 6\nx += 3\n```The final value of x is: 2\n\nWrite a function `compute_final"
      }
    ],
    "correct": false
  },
  {
    "code": "x = 0\nx = int(np.abs(x - 2))\nx //= 6\nx = int(np.abs(x - 4))\nx *= 2\nx %= 3\nx = int(np.abs(x - 6))\nx += 6\nx %= 8\nx = int(np.sqrt(x))\nx -= 7\nx *= 2",
    "intermediate": [
      2,
      0,
      4,
      8,
      2,
      4,
      10,
      2,
      1,
      -6,
      -12
    ],
    "true_val": -12,
    "pred_int": 3,
    "outputs": [
      {
        "generated_text": "You are given a short Python program. Your task is to compute the final value of the variable x. Return only the integer, without commas, an equal sign, or any additional text. The integer should appear immediately after the word 'is: '.\n\n```python\nx = 0\nx = int(np.abs(x - 2))\nx //= 6\nx = int(np.abs(x - 4))\nx *= 2\nx %= 3\nx = int(np.abs(x - 6))\nx += 6\nx %= 8\nx = int(np.sqrt(x))\nx -= 7\nx *= 2\n```The final value of x is: 3\n```python\n\n```\n\n**"
      },
      {
        "generated_text": "You are given a short Python program. Your task is to compute the final value of the variable x. Return only the integer, without commas, an equal sign, or any additional text. The integer should appear immediately after the word 'is: '.\n\n```python\nx = 0\nx = int(np.abs(x - 2))\nx //= 6\nx = int(np.abs(x - 4))\nx *= 2\nx %= 3\nx = int(np.abs(x - 6))\nx += 6\nx %= 8\nx = int(np.sqrt(x))\nx -= 7\nx *= 2\n```The final value of x is: 6"
      },
      {
        "generated_text": "You are given a short Python program. Your task is to compute the final value of the variable x. Return only the integer, without commas, an equal sign, or any additional text. The integer should appear immediately after the word 'is: '.\n\n```python\nx = 0\nx = int(np.abs(x - 2))\nx //= 6\nx = int(np.abs(x - 4))\nx *= 2\nx %= 3\nx = int(np.abs(x - 6))\nx += 6\nx %= 8\nx = int(np.sqrt(x))\nx -= 7\nx *= 2\n```The final value of x is: \n```python\nx = int(np"
      },
      {
        "generated_text": "You are given a short Python program. Your task is to compute the final value of the variable x. Return only the integer, without commas, an equal sign, or any additional text. The integer should appear immediately after the word 'is: '.\n\n```python\nx = 0\nx = int(np.abs(x - 2))\nx //= 6\nx = int(np.abs(x - 4))\nx *= 2\nx %= 3\nx = int(np.abs(x - 6))\nx += 6\nx %= 8\nx = int(np.sqrt(x))\nx -= 7\nx *= 2\n```The final value of x is: \n```\n\n```python\n# Your"
      },
      {
        "generated_text": "You are given a short Python program. Your task is to compute the final value of the variable x. Return only the integer, without commas, an equal sign, or any additional text. The integer should appear immediately after the word 'is: '.\n\n```python\nx = 0\nx = int(np.abs(x - 2))\nx //= 6\nx = int(np.abs(x - 4))\nx *= 2\nx %= 3\nx = int(np.abs(x - 6))\nx += 6\nx %= 8\nx = int(np.sqrt(x))\nx -= 7\nx *= 2\n```The final value of x is: 4\n\nExample:\n\nInput:\n```"
      },
      {
        "generated_text": "You are given a short Python program. Your task is to compute the final value of the variable x. Return only the integer, without commas, an equal sign, or any additional text. The integer should appear immediately after the word 'is: '.\n\n```python\nx = 0\nx = int(np.abs(x - 2))\nx //= 6\nx = int(np.abs(x - 4))\nx *= 2\nx %= 3\nx = int(np.abs(x - 6))\nx += 6\nx %= 8\nx = int(np.sqrt(x))\nx -= 7\nx *= 2\n```The final value of x is: 3\n\nFor the given code, the final value"
      },
      {
        "generated_text": "You are given a short Python program. Your task is to compute the final value of the variable x. Return only the integer, without commas, an equal sign, or any additional text. The integer should appear immediately after the word 'is: '.\n\n```python\nx = 0\nx = int(np.abs(x - 2))\nx //= 6\nx = int(np.abs(x - 4))\nx *= 2\nx %= 3\nx = int(np.abs(x - 6))\nx += 6\nx %= 8\nx = int(np.sqrt(x))\nx -= 7\nx *= 2\n```The final value of x is: \n\nExample:\nInput:\n```python"
      },
      {
        "generated_text": "You are given a short Python program. Your task is to compute the final value of the variable x. Return only the integer, without commas, an equal sign, or any additional text. The integer should appear immediately after the word 'is: '.\n\n```python\nx = 0\nx = int(np.abs(x - 2))\nx //= 6\nx = int(np.abs(x - 4))\nx *= 2\nx %= 3\nx = int(np.abs(x - 6))\nx += 6\nx %= 8\nx = int(np.sqrt(x))\nx -= 7\nx *= 2\n```The final value of x is: \n``` \n2 \n```"
      },
      {
        "generated_text": "You are given a short Python program. Your task is to compute the final value of the variable x. Return only the integer, without commas, an equal sign, or any additional text. The integer should appear immediately after the word 'is: '.\n\n```python\nx = 0\nx = int(np.abs(x - 2))\nx //= 6\nx = int(np.abs(x - 4))\nx *= 2\nx %= 3\nx = int(np.abs(x - 6))\nx += 6\nx %= 8\nx = int(np.sqrt(x))\nx -= 7\nx *= 2\n```The final value of x is: 7\n```python\n\nx = 0"
      },
      {
        "generated_text": "You are given a short Python program. Your task is to compute the final value of the variable x. Return only the integer, without commas, an equal sign, or any additional text. The integer should appear immediately after the word 'is: '.\n\n```python\nx = 0\nx = int(np.abs(x - 2))\nx //= 6\nx = int(np.abs(x - 4))\nx *= 2\nx %= 3\nx = int(np.abs(x - 6))\nx += 6\nx %= 8\nx = int(np.sqrt(x))\nx -= 7\nx *= 2\n```The final value of x is: 3\n\n```python\nx = 0"
      }
    ],
    "correct": false
  },
  {
    "code": "x = 0\nx //= 3\nx -= 4\nx //= 5\nx -= 8\nx %= 5\nx += 8\nx //= 2\nx -= 5\nx **= 2",
    "intermediate": [
      0,
      -4,
      -1,
      -9,
      1,
      9,
      4,
      -1,
      1
    ],
    "true_val": 1,
    "pred_int": 0,
    "outputs": [
      {
        "generated_text": "You are given a short Python program. Your task is to compute the final value of the variable x. Return only the integer, without commas, an equal sign, or any additional text. The integer should appear immediately after the word 'is: '.\n\n```python\nx = 0\nx //= 3\nx -= 4\nx //= 5\nx -= 8\nx %= 5\nx += 8\nx //= 2\nx -= 5\nx **= 2\n```The final value of x is: \n\n```python\nprint(\"The final value"
      },
      {
        "generated_text": "You are given a short Python program. Your task is to compute the final value of the variable x. Return only the integer, without commas, an equal sign, or any additional text. The integer should appear immediately after the word 'is: '.\n\n```python\nx = 0\nx //= 3\nx -= 4\nx //= 5\nx -= 8\nx %= 5\nx += 8\nx //= 2\nx -= 5\nx **= 2\n```The final value of x is: 19\n\nYour code should be able to handle any"
      },
      {
        "generated_text": "You are given a short Python program. Your task is to compute the final value of the variable x. Return only the integer, without commas, an equal sign, or any additional text. The integer should appear immediately after the word 'is: '.\n\n```python\nx = 0\nx //= 3\nx -= 4\nx //= 5\nx -= 8\nx %= 5\nx += 8\nx //= 2\nx -= 5\nx **= 2\n```The final value of x is: 22\n```python\nx //= "
      },
      {
        "generated_text": "You are given a short Python program. Your task is to compute the final value of the variable x. Return only the integer, without commas, an equal sign, or any additional text. The integer should appear immediately after the word 'is: '.\n\n```python\nx = 0\nx //= 3\nx -= 4\nx //= 5\nx -= 8\nx %= 5\nx += 8\nx //= 2\nx -= 5\nx **= 2\n```The final value of x is: 14\n\nExplanation:\nThe initial value"
      },
      {
        "generated_text": "You are given a short Python program. Your task is to compute the final value of the variable x. Return only the integer, without commas, an equal sign, or any additional text. The integer should appear immediately after the word 'is: '.\n\n```python\nx = 0\nx //= 3\nx -= 4\nx //= 5\nx -= 8\nx %= 5\nx += 8\nx //= 2\nx -= 5\nx **= 2\n```The final value of x is: 42"
      },
      {
        "generated_text": "You are given a short Python program. Your task is to compute the final value of the variable x. Return only the integer, without commas, an equal sign, or any additional text. The integer should appear immediately after the word 'is: '.\n\n```python\nx = 0\nx //= 3\nx -= 4\nx //= 5\nx -= 8\nx %= 5\nx += 8\nx //= 2\nx -= 5\nx **= 2\n```The final value of x is: \n```markdown\n2\n```"
      },
      {
        "generated_text": "You are given a short Python program. Your task is to compute the final value of the variable x. Return only the integer, without commas, an equal sign, or any additional text. The integer should appear immediately after the word 'is: '.\n\n```python\nx = 0\nx //= 3\nx -= 4\nx //= 5\nx -= 8\nx %= 5\nx += 8\nx //= 2\nx -= 5\nx **= 2\n```The final value of x is: \n\nNote: The operators used in the program are"
      },
      {
        "generated_text": "You are given a short Python program. Your task is to compute the final value of the variable x. Return only the integer, without commas, an equal sign, or any additional text. The integer should appear immediately after the word 'is: '.\n\n```python\nx = 0\nx //= 3\nx -= 4\nx //= 5\nx -= 8\nx %= 5\nx += 8\nx //= 2\nx -= 5\nx **= 2\n```The final value of x is: \n\n```python\nprint(x)\n"
      },
      {
        "generated_text": "You are given a short Python program. Your task is to compute the final value of the variable x. Return only the integer, without commas, an equal sign, or any additional text. The integer should appear immediately after the word 'is: '.\n\n```python\nx = 0\nx //= 3\nx -= 4\nx //= 5\nx -= 8\nx %= 5\nx += 8\nx //= 2\nx -= 5\nx **= 2\n```The final value of x is: 0\n```python\nx = 0"
      },
      {
        "generated_text": "You are given a short Python program. Your task is to compute the final value of the variable x. Return only the integer, without commas, an equal sign, or any additional text. The integer should appear immediately after the word 'is: '.\n\n```python\nx = 0\nx //= 3\nx -= 4\nx //= 5\nx -= 8\nx %= 5\nx += 8\nx //= 2\nx -= 5\nx **= 2\n```The final value of x is: \n```python\nprint(f\"The"
      }
    ],
    "correct": false
  },
  {
    "code": "x = 0\nx = int(np.sqrt(x))\nx += 3\nx %= 4\nx **= 2\nx -= 8\nx //= 1\nx %= 1\nx *= 3\nx += 1\nx = int(np.abs(x - 7))\nx //= 9\nx = int(np.abs(x - 7))",
    "intermediate": [
      0,
      3,
      3,
      9,
      1,
      1,
      0,
      0,
      1,
      6,
      0,
      7
    ],
    "true_val": 7,
    "pred_int": 0,
    "outputs": [
      {
        "generated_text": "You are given a short Python program. Your task is to compute the final value of the variable x. Return only the integer, without commas, an equal sign, or any additional text. The integer should appear immediately after the word 'is: '.\n\n```python\nx = 0\nx = int(np.sqrt(x))\nx += 3\nx %= 4\nx **= 2\nx -= 8\nx //= 1\nx %= 1\nx *= 3\nx += 1\nx = int(np.abs(x - 7))\nx //= 9\nx = int(np.abs(x - 7))\n```The final value of x is: \n\n```python\nx = 0\n"
      },
      {
        "generated_text": "You are given a short Python program. Your task is to compute the final value of the variable x. Return only the integer, without commas, an equal sign, or any additional text. The integer should appear immediately after the word 'is: '.\n\n```python\nx = 0\nx = int(np.sqrt(x))\nx += 3\nx %= 4\nx **= 2\nx -= 8\nx //= 1\nx %= 1\nx *= 3\nx += 1\nx = int(np.abs(x - 7))\nx //= 9\nx = int(np.abs(x - 7))\n```The final value of x is: 6\n\nExplanation:\nx = "
      },
      {
        "generated_text": "You are given a short Python program. Your task is to compute the final value of the variable x. Return only the integer, without commas, an equal sign, or any additional text. The integer should appear immediately after the word 'is: '.\n\n```python\nx = 0\nx = int(np.sqrt(x))\nx += 3\nx %= 4\nx **= 2\nx -= 8\nx //= 1\nx %= 1\nx *= 3\nx += 1\nx = int(np.abs(x - 7))\nx //= 9\nx = int(np.abs(x - 7))\n```The final value of x is: 0\n```python\ndef compute_final"
      },
      {
        "generated_text": "You are given a short Python program. Your task is to compute the final value of the variable x. Return only the integer, without commas, an equal sign, or any additional text. The integer should appear immediately after the word 'is: '.\n\n```python\nx = 0\nx = int(np.sqrt(x))\nx += 3\nx %= 4\nx **= 2\nx -= 8\nx //= 1\nx %= 1\nx *= 3\nx += 1\nx = int(np.abs(x - 7))\nx //= 9\nx = int(np.abs(x - 7))\n```The final value of x is: 0\n\n```python\nx = 0"
      },
      {
        "generated_text": "You are given a short Python program. Your task is to compute the final value of the variable x. Return only the integer, without commas, an equal sign, or any additional text. The integer should appear immediately after the word 'is: '.\n\n```python\nx = 0\nx = int(np.sqrt(x))\nx += 3\nx %= 4\nx **= 2\nx -= 8\nx //= 1\nx %= 1\nx *= 3\nx += 1\nx = int(np.abs(x - 7))\nx //= 9\nx = int(np.abs(x - 7))\n```The final value of x is: 6"
      },
      {
        "generated_text": "You are given a short Python program. Your task is to compute the final value of the variable x. Return only the integer, without commas, an equal sign, or any additional text. The integer should appear immediately after the word 'is: '.\n\n```python\nx = 0\nx = int(np.sqrt(x))\nx += 3\nx %= 4\nx **= 2\nx -= 8\nx //= 1\nx %= 1\nx *= 3\nx += 1\nx = int(np.abs(x - 7))\nx //= 9\nx = int(np.abs(x - 7))\n```The final value of x is: 1\n```python\nx = 0"
      },
      {
        "generated_text": "You are given a short Python program. Your task is to compute the final value of the variable x. Return only the integer, without commas, an equal sign, or any additional text. The integer should appear immediately after the word 'is: '.\n\n```python\nx = 0\nx = int(np.sqrt(x))\nx += 3\nx %= 4\nx **= 2\nx -= 8\nx //= 1\nx %= 1\nx *= 3\nx += 1\nx = int(np.abs(x - 7))\nx //= 9\nx = int(np.abs(x - 7))\n```The final value of x is: 0\nThe final value of x is: "
      },
      {
        "generated_text": "You are given a short Python program. Your task is to compute the final value of the variable x. Return only the integer, without commas, an equal sign, or any additional text. The integer should appear immediately after the word 'is: '.\n\n```python\nx = 0\nx = int(np.sqrt(x))\nx += 3\nx %= 4\nx **= 2\nx -= 8\nx //= 1\nx %= 1\nx *= 3\nx += 1\nx = int(np.abs(x - 7))\nx //= 9\nx = int(np.abs(x - 7))\n```The final value of x is: 1\n```python\nx = 0"
      },
      {
        "generated_text": "You are given a short Python program. Your task is to compute the final value of the variable x. Return only the integer, without commas, an equal sign, or any additional text. The integer should appear immediately after the word 'is: '.\n\n```python\nx = 0\nx = int(np.sqrt(x))\nx += 3\nx %= 4\nx **= 2\nx -= 8\nx //= 1\nx %= 1\nx *= 3\nx += 1\nx = int(np.abs(x - 7))\nx //= 9\nx = int(np.abs(x - 7))\n```The final value of x is: 6\n\nWrite a program to compute the final value"
      },
      {
        "generated_text": "You are given a short Python program. Your task is to compute the final value of the variable x. Return only the integer, without commas, an equal sign, or any additional text. The integer should appear immediately after the word 'is: '.\n\n```python\nx = 0\nx = int(np.sqrt(x))\nx += 3\nx %= 4\nx **= 2\nx -= 8\nx //= 1\nx %= 1\nx *= 3\nx += 1\nx = int(np.abs(x - 7))\nx //= 9\nx = int(np.abs(x - 7))\n```The final value of x is: 3\n```\n\n### Created Chinese Question"
      }
    ],
    "correct": false
  }
]